fastfm2/__init__.py
fastfm2/als/__init__.py
fastfm2/als/regression.py
fastfm2/base.py
fastfm2/core/cpp_ffm.pxd
fastfm2/core/ffm2.cpp
fastfm2/core/ffm2.pyx
fastfm2/core/pre_release.pxi
fastfm2/datasets.py
fastfm2/tests/__init__.py
fastfm2/tests/test_als.py
fastfm2/tests/test_base.py
fastfm2/validation.py
ffm2.cp37-win32.pyd
fastfm2-0.5.2.dist-info/LICENSE
fastfm2-0.5.2.dist-info/WHEEL
fastfm2-0.5.2.dist-info/METADATA
fastfm2-0.5.2.dist-info/RECORD
