Metadata-Version: 2.1
Name: fastfm2
Version: 0.5.2
Summary: A Library for Factorization Machines
Home-page: https://github.com/palaimon/fastfm2
License: GNU AGPLv3
Author: palaimon.io
Author-email: oss@mail.palaimon.io
Requires-Python: >=3.6,<4.0
Classifier: License :: Other/Proprietary License
Classifier: Programming Language :: Python :: 3
Classifier: Programming Language :: Python :: 3.6
Classifier: Programming Language :: Python :: 3.7
Classifier: Programming Language :: Python :: 3.8
Classifier: Programming Language :: Python :: 3.9
Requires-Dist: numpy (<1.20)
Requires-Dist: scikit-learn (>=0.22.1,<0.23.0)
Requires-Dist: scipy (>=1.3,<2.0)
Project-URL: Repository, https://github.com/palaimon/fastfm2
